pythae/__init__.py
pythae/config.py
pythae/customexception.py
pythae/data/__init__.py
pythae/data/datasets.py
pythae/data/preprocessors.py
pythae/models/__init__.py
pythae/models/adversarial_ae/__init__.py
pythae/models/adversarial_ae/adversarial_ae_config.py
pythae/models/adversarial_ae/adversarial_ae_model.py
pythae/models/ae/__init__.py
pythae/models/ae/ae_config.py
pythae/models/ae/ae_model.py
pythae/models/auto_model/__init__.py
pythae/models/auto_model/auto_config.py
pythae/models/auto_model/auto_model.py
pythae/models/base/__init__.py
pythae/models/base/base_config.py
pythae/models/base/base_model.py
pythae/models/base/base_utils.py
pythae/models/beta_tc_vae/__init__.py
pythae/models/beta_tc_vae/beta_tc_vae_config.py
pythae/models/beta_tc_vae/beta_tc_vae_model.py
pythae/models/beta_vae/__init__.py
pythae/models/beta_vae/beta_vae_config.py
pythae/models/beta_vae/beta_vae_model.py
pythae/models/ciwae/__init__.py
pythae/models/ciwae/ciwae_config.py
pythae/models/ciwae/ciwae_model.py
pythae/models/disentangled_beta_vae/__init__.py
pythae/models/disentangled_beta_vae/disentangled_beta_vae_config.py
pythae/models/disentangled_beta_vae/disentangled_beta_vae_model.py
pythae/models/factor_vae/__init__.py
pythae/models/factor_vae/factor_vae_config.py
pythae/models/factor_vae/factor_vae_model.py
pythae/models/factor_vae/factor_vae_utils.py
pythae/models/hvae/__init__.py
pythae/models/hvae/hvae_config.py
pythae/models/hvae/hvae_model.py
pythae/models/info_vae/__init__.py
pythae/models/info_vae/info_vae_config.py
pythae/models/info_vae/info_vae_model.py
pythae/models/iwae/__init__.py
pythae/models/iwae/iwae_config.py
pythae/models/iwae/iwae_model.py
pythae/models/miwae/__init__.py
pythae/models/miwae/miwae_config.py
pythae/models/miwae/miwae_model.py
pythae/models/msssim_vae/__init__.py
pythae/models/msssim_vae/msssim_vae_config.py
pythae/models/msssim_vae/msssim_vae_model.py
pythae/models/msssim_vae/msssim_vae_utils.py
pythae/models/nn/__init__.py
pythae-0.1.2.dist-info/LICENSE
pythae-0.1.2.dist-info/METADATA
pythae-0.1.2.dist-info/WHEEL
pythae-0.1.2.dist-info/top_level.txt
pythae-0.1.2.dist-info/RECORD
