Metadata-Version: 2.1
Name: pythae
Version: 0.1.2
Summary: Unifying Generative Autoencoders in Python
Home-page: https://github.com/clementchadebec/benchmark_VAE
Author: Clement Chadebec (HekA team INRIA)
Author-email: clement.chadebec@inria.fr
Project-URL: Bug Tracker, https://github.com/clementchadebec/benchmark_VAE/issues
Classifier: Programming Language :: Python :: 3
Classifier: Programming Language :: Python :: 3.7
Classifier: Programming Language :: Python :: 3.8
Classifier: Programming Language :: Python :: 3.9
Classifier: License :: OSI Approved :: Apache Software License
Classifier: Operating System :: OS Independent
Requires-Python: >=3.7
License-File: LICENSE
Requires-Dist: cloudpickle >=2.1.0
Requires-Dist: imageio
Requires-Dist: numpy >=1.19
Requires-Dist: pydantic >=2.0
Requires-Dist: scikit-learn
Requires-Dist: scipy >=1.7.1
Requires-Dist: torch >=1.10.1
Requires-Dist: tqdm
Requires-Dist: typing-extensions
Requires-Dist: dataclasses >=0.6
Requires-Dist: pickle5 ; python_version == "3.7.*"
